OWLPy/__init__.py
OWLPy/driver.py
OWLPy/objects.py
OWLPy/errors/__init__.py
OWLPy/errors/customerrors.py
OWLPy/models/__init__.py
OWLPy-0.2.5.dist-info/LICENSE.txt
OWLPy-0.2.5.dist-info/METADATA
OWLPy-0.2.5.dist-info/WHEEL
OWLPy-0.2.5.dist-info/top_level.txt
OWLPy-0.2.5.dist-info/RECORD
