Metadata-Version: 2.1
Name: OWLPy
Version: 0.2.5
Summary: Python Driver and Models for the OWL API
Home-page: https://github.com/spydernaz/OWLPy.py
Author: Nathaniel Vala
Author-email: nathanielvala@hotmail.com
License: MIT
Keywords: API,OWL,Overwatch,Overwatch League
Platform: UNKNOWN
Classifier: Development Status :: 3 - Alpha
Classifier: Intended Audience :: Developers
Classifier: Topic :: Software Development :: Build Tools
Classifier: License :: OSI Approved :: MIT License
Classifier: Programming Language :: Python :: 3
Classifier: Programming Language :: Python :: 3.4
Classifier: Programming Language :: Python :: 3.5
Classifier: Programming Language :: Python :: 3.6
Classifier: Programming Language :: Python :: 3.7
